{
  "timestamp": "2025-09-24 23:34:32",
  "config": {
    "model": "sentence-transformers/all-MiniLM-L6-v2",
    "batch_size": 1024,
    "normalize": true,
    "top_k_neighbors": 50,
    "similarity_threshold_initial": 0.3,
    "similarity_threshold_used": 0.44999992847442627,
    "hnsw": {
      "M": 16,
      "ef_construction": 200,
      "ef": 200
    },
    "query_batch_size": 25000,
    "tuning": {
      "enabled": true,
      "csv": null,
      "min_precision": 0.9,
      "min_recall": null,
      "grid": [
        0.05,
        0.95,
        0.01
      ],
      "metrics_csv": "romance-novel-nlp-research/src/eda_analysis/outputs/similarity_threshold_metrics.csv",
      "summary_json": "romance-novel-nlp-research/src/eda_analysis/outputs/similarity_threshold_summary.json",
      "autogen_used": true
    },
    "extras": {
      "add_string_metrics": false,
      "use_rapidfuzz": true,
      "metrics_sample_n": null
    }
  },
  "stats": {
    "total_tokens": 254778,
    "embedding_dim": 384,
    "candidate_pairs_found": 12502616
  },
  "outputs": {
    "candidate_pairs_file": "romance-novel-nlp-research/src/eda_analysis/outputs/candidate_similarity_pairs.parquet",
    "sample_file": "romance-novel-nlp-research/src/eda_analysis/outputs/similarity_sample_inspection.parquet"
  }
}